cachehash/__init__.py
cachehash/main.py
cachehash/sql/delete_record.sql
cachehash/sql/get_record.sql
cachehash/sql/get_record_hash_key.sql
cachehash/sql/get_record_key.sql
cachehash/sql/insert_record.sql
cachehash/sql/make_table.sql
cachehash/sql/update_record.sql
cachehash-1.1.3.dist-info/METADATA
cachehash-1.1.3.dist-info/WHEEL
cachehash-1.1.3.dist-info/licenses/LICENSE
cachehash-1.1.3.dist-info/RECORD
