Metadata-Version: 2.4
Name: cachehash
Version: 1.1.3
Summary: This tool memoizes data to sqlite.
Project-URL: Homepage, https://github.com/VerinFast/cachehash
Project-URL: Bug Tracker, https://github.com/VerinFast/cachehash/issues
Project-URL: Source, https://github.com/VerinFast/cachehash
Author-email: Jason Nichols <github@verinfast.com>, Sean Conrad <github@verinfast.com>
License-File: LICENSE
Classifier: License :: Free for non-commercial use
Classifier: Operating System :: OS Independent
Classifier: Programming Language :: Python :: 3
Requires-Python: <3.14,>=3.9
Requires-Dist: xxhash>=3.5.0
Provides-Extra: dev
Requires-Dist: black>=24.1.1; extra == 'dev'
Requires-Dist: coverage~=7.10.3; extra == 'dev'
Requires-Dist: pytest; extra == 'dev'
Requires-Dist: pytest-cov; extra == 'dev'
